WPP/__init__.py
WPP/__main__.py
WPP/main.py
wpp_tools-0.3.6.dist-info/METADATA
wpp_tools-0.3.6.dist-info/WHEEL
wpp_tools-0.3.6.dist-info/top_level.txt
wpp_tools-0.3.6.dist-info/RECORD
