Metadata-Version: 2.4
Name: WPP-tools
Version: 0.3.6
Author: William Olson
Author-email: Blueshadow0324@gmail.com
Requires-Dist: streamlit
Dynamic: author
Dynamic: author-email
Dynamic: description
Dynamic: description-content-type
Dynamic: requires-dist
